<?xml version="1.0" encoding="UTF-8" ?>        
        <XML>
            <Content>UPDATE</Content>
            <Clip>
                <ClipName>PRCPCDP0126</ClipName>
                <TipoContenido>PROMOS CAPITULARES</TipoContenido>
                <Contenido><![CDATA[ CDP MAYRA MARTELL  LUNES 08 SEP 20:30 Hrs]]></Contenido>
                <OriginalTitle></OriginalTitle>
                <Description> </Description>
                <Notes>a</Notes>
                <DurPrev></DurPrev>
                <Chapter></Chapter>
                <EndDate></EndDate>
                <EPG></EPG>
                <EPG_Content> </EPG_Content>
                <Segments>
            
                <Segment>
                    <SegTitle>1-1 CRUCE DE PALABRAS - CDP MAYRA MARTELL  LUNES 08 SEP 20:30 Hrs</SegTitle>
                    <MediaID>PRCPCDP0126</MediaID>
                    <Duration>00:00:20.00</Duration>
                    <SegNumber>1</SegNumber>
                    <ClipGroup>PROMO</ClipGroup>
                    <Description> </Description>
                </Segment>
            </Segments></Clip></XML>