<?xml version="1.0" encoding="UTF-8" ?>        
        <XML>
            <Content>UPDATE</Content>
            <Clip>
                <ClipName>PRCSPSU0209</ClipName>
                <TipoContenido>PROMOS CAPSULAS</TipoContenido>
                <Contenido><![CDATA[ PALESTINA KABCHI VERSION 1]]></Contenido>
                <OriginalTitle></OriginalTitle>
                <Description> </Description>
                <Notes>a</Notes>
                <DurPrev></DurPrev>
                <Chapter></Chapter>
                <EndDate></EndDate>
                <EPG></EPG>
                <EPG_Content> </EPG_Content>
                <Segments>
            
                <Segment>
                    <SegTitle>1-1 CAPSULAS - PALESTINA KABCHI VERSION 1</SegTitle>
                    <MediaID>PRCSPSU0209</MediaID>
                    <Duration>00:01:00.00</Duration>
                    <SegNumber>1</SegNumber>
                    <ClipGroup>PROMO</ClipGroup>
                    <Description> </Description>
                </Segment>
            </Segments></Clip></XML>